pou/online/__init__.py
pou/online/account.py
pou/online/client.py
pou/online/common.py
pou/online/errors.py
pou/online/request.py
pou/online/site.py
pou/online/user.py
pou/pvp/__init__.py
pou/pvp/discovery.py
pou/pvp/host.py
pou/pvp/settings.py
pouclients-0.1.0.dist-info/LICENSE
pouclients-0.1.0.dist-info/METADATA
pouclients-0.1.0.dist-info/WHEEL
pouclients-0.1.0.dist-info/top_level.txt
pouclients-0.1.0.dist-info/RECORD
