Metadata-Version: 2.1
Name: pouclients
Version: 0.1.0
Summary: Network library for Pou game servers
Author-email: DaniElectra <danielectra@outlook.com>
License: MIT
License-File: LICENSE
Requires-Dist: requests
